nevermined_sdk_py/__init__.py
nevermined_sdk_py/config.py
nevermined_sdk_py/config_provider.py
nevermined_sdk_py/agreement_events/__init__.py
nevermined_sdk_py/agreement_events/access_agreement.py
nevermined_sdk_py/agreement_events/compute_agreement.py
nevermined_sdk_py/agreement_events/payments.py
nevermined_sdk_py/assets/__init__.py
nevermined_sdk_py/assets/asset_consumer.py
nevermined_sdk_py/assets/asset_executor.py
nevermined_sdk_py/data_store/__init__.py
nevermined_sdk_py/data_store/auth_tokens.py
nevermined_sdk_py/faucet/__init__.py
nevermined_sdk_py/faucet/faucet.py
nevermined_sdk_py/gateway/__init__.py
nevermined_sdk_py/gateway/gateway.py
nevermined_sdk_py/gateway/gateway_provider.py
nevermined_sdk_py/nevermined/__init__.py
nevermined_sdk_py/nevermined/accounts.py
nevermined_sdk_py/nevermined/agreements.py
nevermined_sdk_py/nevermined/assets.py
nevermined_sdk_py/nevermined/auth.py
nevermined_sdk_py/nevermined/conditions.py
nevermined_sdk_py/nevermined/files.py
nevermined_sdk_py/nevermined/keeper.py
nevermined_sdk_py/nevermined/nevermined.py
nevermined_sdk_py/nevermined/nfts.py
nevermined_sdk_py/nevermined/provenance.py
nevermined_sdk_py/nevermined/providers.py
nevermined_sdk_py/nevermined/secret_store.py
nevermined_sdk_py/nevermined/services.py
nevermined_sdk_py/nevermined/templates.py
nevermined_sdk_py/nevermined/tokens.py
nevermined_sdk_py/secret_store/__init__.py
nevermined_sdk_py/secret_store/secret_store.py
nevermined_sdk_py/secret_store/secret_store_provider.py
nevermined_sdk_py-0.14.0.dist-info/LICENSE
nevermined_sdk_py-0.14.0.dist-info/METADATA
nevermined_sdk_py-0.14.0.dist-info/NOTICE
nevermined_sdk_py-0.14.0.dist-info/WHEEL
nevermined_sdk_py-0.14.0.dist-info/top_level.txt
nevermined_sdk_py-0.14.0.dist-info/RECORD
