Metadata-Version: 2.1
Name: nevermined-sdk-py
Version: 0.14.0
Summary: 🐳 Nevermined Python SDK.
Home-page: https://github.com/nevermined-io/sdk-py
Author: nevermined-io
Author-email: root@nevermined.io
License: Apache Software License 2.0
Keywords: nevermined-sdk-py
Platform: UNKNOWN
Classifier: Development Status :: 5 - Production/Stable
Classifier: Intended Audience :: Developers
Classifier: License :: OSI Approved :: Apache Software License
Classifier: Natural Language :: English
Classifier: Programming Language :: Python :: 3.7
License-File: LICENSE
License-File: NOTICE
Requires-Dist: coloredlogs
Requires-Dist: pyopenssl
Requires-Dist: PyJWT
Requires-Dist: PyYAML (>=5.2)
Requires-Dist: common-utils-py (==1.0.0)
Requires-Dist: contracts-lib-py (==1.0.0)
Requires-Dist: nevermined-secret-store (==0.1.1)
Requires-Dist: requests (>=2.21.0)
Requires-Dist: deprecated
Requires-Dist: pycryptodomex
Requires-Dist: tqdm
Requires-Dist: pytz
Requires-Dist: web3 (==5.26.0)
Provides-Extra: dev
Requires-Dist: bumpversion ; extra == 'dev'
Requires-Dist: pkginfo ; extra == 'dev'
Requires-Dist: twine ; extra == 'dev'
Requires-Dist: watchdog ; extra == 'dev'
Requires-Dist: coverage ; extra == 'dev'
Requires-Dist: pylint ; extra == 'dev'
Requires-Dist: pytest ; extra == 'dev'
Requires-Dist: pytest-watch ; extra == 'dev'
Requires-Dist: Sphinx ; extra == 'dev'
Requires-Dist: sphinxcontrib-apidoc ; extra == 'dev'
Provides-Extra: docs
Requires-Dist: Sphinx ; extra == 'docs'
Requires-Dist: sphinxcontrib-apidoc ; extra == 'docs'
Provides-Extra: test
Requires-Dist: coverage ; extra == 'test'
Requires-Dist: pylint ; extra == 'test'
Requires-Dist: pytest ; extra == 'test'
Requires-Dist: pytest-watch ; extra == 'test'
